aws_check_for_domain_hijacking.py
aws_check_for_domain_hijacking-0.1.dist-info/DESCRIPTION.rst
aws_check_for_domain_hijacking-0.1.dist-info/METADATA
aws_check_for_domain_hijacking-0.1.dist-info/RECORD
aws_check_for_domain_hijacking-0.1.dist-info/WHEEL
aws_check_for_domain_hijacking-0.1.dist-info/metadata.json
aws_check_for_domain_hijacking-0.1.dist-info/top_level.txt
